<?xml version='1.0' encoding='UTF-8'?><factura version='1.1.0' id='comprobante'><infoTributaria><ambiente>2</ambiente><tipoEmision>1</tipoEmision><razonSocial>BUELE SARMIENTO MARIA EUGENIA</razonSocial><nombreComercial>IMPORTADORA BYC LA EXCLUSIVIDAD PARA TU HOGAR TRAMONTINA</nombreComercial><ruc>0704384098001</ruc><claveAcceso>0106202301070438409800120010010000002061234567811</claveAcceso><codDoc>01</codDoc><estab>001</estab><ptoEmi>001</ptoEmi><secuencial>000000206</secuencial><dirMatriz>AV. HURTADO DE MEDOZA 10-72 Y BULAN. JUNTO A LA ITALIANA</dirMatriz></infoTributaria><infoFactura><fechaEmision>01/06/2023</fechaEmision><dirEstablecimiento>AV. HURTADO DE MEDOZA 10-72 Y BULAN. JUNTO A LA ITALIANA</dirEstablecimiento><obligadoContabilidad>NO</obligadoContabilidad><tipoIdentificacionComprador>04</tipoIdentificacionComprador><razonSocialComprador>GRANJA ARREAGA SHIRLEY SUGEY</razonSocialComprador><identificacionComprador>0922307962001</identificacionComprador><totalSinImpuestos>480.44</totalSinImpuestos><totalDescuento>0</totalDescuento><totalConImpuestos><totalImpuesto><codigo>2</codigo><codigoPorcentaje>2</codigoPorcentaje><baseImponible>480.44</baseImponible><valor>57.65</valor></totalImpuesto></totalConImpuestos><propina>0.00</propina><importeTotal>538.09</importeTotal><moneda>DOLAR</moneda><pagos><pago><formaPago>20</formaPago><total>538.09</total></pago></pagos></infoFactura><detalles><detalle><codigoPrincipal>23731004</codigoPrincipal><codigoAuxiliar>FAM.TIP.057</codigoAuxiliar><descripcion>CUCHILLO DE MESA MALIBU Y BUZIOS</descripcion><cantidad>3</cantidad><precioUnitario>7.83</precioUnitario><descuento>0</descuento><precioTotalSinImpuesto>23.49</precioTotalSinImpuesto><impuestos><impuesto><codigo>2</codigo><codigoPorcentaje>2</codigoPorcentaje><tarifa>12</tarifa><baseImponible>23.49</baseImponible><valor>2.82</valor></impuesto></impuestos></detalle><detalle><codigoPrincipal>24620080</codigoPrincipal><codigoAuxiliar>FAM.TIP.241</codigoAuxiliar><descripcion>CUCHULLO PREOFESIONAL 10</descripcion><cantidad>3</cantidad><precioUnitario>8.3</precioUnitario><descuento>0</descuento><precioTotalSinImpuesto>24.9</precioTotalSinImpuesto><impuestos><impuesto><codigo>2</codigo><codigoPorcentaje>2</codigoPorcentaje><tarifa>12</tarifa><baseImponible>24.9</baseImponible><valor>2.99</valor></impuesto></impuestos></detalle><detalle><codigoPrincipal>62504160</codigoPrincipal><codigoAuxiliar>FAM.TIP.017</codigoAuxiliar><descripcion>CACEROLA HONDA 16CM SOLAR</descripcion><cantidad>2</cantidad><precioUnitario>21.88</precioUnitario><descuento>0</descuento><precioTotalSinImpuesto>43.76</precioTotalSinImpuesto><impuestos><impuesto><codigo>2</codigo><codigoPorcentaje>2</codigoPorcentaje><tarifa>12</tarifa><baseImponible>43.76</baseImponible><valor>5.25</valor></impuesto></impuestos></detalle><detalle><codigoPrincipal>65510200</codigoPrincipal><codigoAuxiliar>FAM.TIP.011</codigoAuxiliar><descripcion>BATERIA DE COCINA 6PZAS. SOLAR</descripcion><cantidad>1</cantidad><precioUnitario>111.52</precioUnitario><descuento>0</descuento><precioTotalSinImpuesto>111.52</precioTotalSinImpuesto><impuestos><impuesto><codigo>2</codigo><codigoPorcentaje>2</codigoPorcentaje><tarifa>12</tarifa><baseImponible>111.52</baseImponible><valor>13.38</valor></impuesto></impuestos></detalle><detalle><codigoPrincipal>65650324</codigoPrincipal><codigoAuxiliar>FAM.TIP.008</codigoAuxiliar><descripcion>BATERIA DE COCINA 4PZ ALLEGRA</descripcion><cantidad>1</cantidad><precioUnitario>66.97</precioUnitario><descuento>0</descuento><precioTotalSinImpuesto>66.97</precioTotalSinImpuesto><impuestos><impuesto><codigo>2</codigo><codigoPorcentaje>2</codigoPorcentaje><tarifa>12</tarifa><baseImponible>66.97</baseImponible><valor>8.04</valor></impuesto></impuestos></detalle><detalle><codigoPrincipal>62504200</codigoPrincipal><codigoAuxiliar>FAM.TIP.020</codigoAuxiliar><descripcion>CACEROLA HONDA 20CM SOLAR</descripcion><cantidad>2</cantidad><precioUnitario>28.13</precioUnitario><descuento>0</descuento><precioTotalSinImpuesto>56.26</precioTotalSinImpuesto><impuestos><impuesto><codigo>2</codigo><codigoPorcentaje>2</codigoPorcentaje><tarifa>12</tarifa><baseImponible>56.26</baseImponible><valor>6.75</valor></impuesto></impuestos></detalle><detalle><codigoPrincipal>23498917</codigoPrincipal><codigoAuxiliar>FAM.TIP.112</codigoAuxiliar><descripcion>JUEGO CUHILLO 8 PIEZAS</descripcion><cantidad>2</cantidad><precioUnitario>10.71</precioUnitario><descuento>0</descuento><precioTotalSinImpuesto>21.42</precioTotalSinImpuesto><impuestos><impuesto><codigo>2</codigo><codigoPorcentaje>2</codigoPorcentaje><tarifa>12</tarifa><baseImponible>21.42</baseImponible><valor>2.57</valor></impuesto></impuestos></detalle><detalle><codigoPrincipal>23498332</codigoPrincipal><codigoAuxiliar>FAM.TIP.118</codigoAuxiliar><descripcion>JUEGO DE CUHILLOS 8 PZAS PLENUS</descripcion><cantidad>2</cantidad><precioUnitario>12.14</precioUnitario><descuento>0</descuento><precioTotalSinImpuesto>24.28</precioTotalSinImpuesto><impuestos><impuesto><codigo>2</codigo><codigoPorcentaje>2</codigoPorcentaje><tarifa>12</tarifa><baseImponible>24.28</baseImponible><valor>2.91</valor></impuesto></impuestos></detalle><detalle><codigoPrincipal>62503200</codigoPrincipal><codigoAuxiliar>FAM.TIP.014</codigoAuxiliar><descripcion>CACEROLA 20CM SOLAR</descripcion><cantidad>3</cantidad><precioUnitario>25.75</precioUnitario><descuento>0</descuento><precioTotalSinImpuesto>77.25</precioTotalSinImpuesto><impuestos><impuesto><codigo>2</codigo><codigoPorcentaje>2</codigoPorcentaje><tarifa>12</tarifa><baseImponible>77.25</baseImponible><valor>9.27</valor></impuesto></impuestos></detalle><detalle><codigoPrincipal>23498826</codigoPrincipal><codigoAuxiliar>FAM.TIP.113</codigoAuxiliar><descripcion>JUEGO DE 3 CUCHILLO PLENUS</descripcion><cantidad>1</cantidad><precioUnitario>5.36</precioUnitario><descuento>0</descuento><precioTotalSinImpuesto>5.36</precioTotalSinImpuesto><impuestos><impuesto><codigo>2</codigo><codigoPorcentaje>2</codigoPorcentaje><tarifa>12</tarifa><baseImponible>5.36</baseImponible><valor>0.64</valor></impuesto></impuestos></detalle><detalle><codigoPrincipal>23736000</codigoPrincipal><descripcion>CUCHARA CAFE MALIBU</descripcion><cantidad>3</cantidad><precioUnitario>3.42</precioUnitario><descuento>0</descuento><precioTotalSinImpuesto>10.26</precioTotalSinImpuesto><impuestos><impuesto><codigo>2</codigo><codigoPorcentaje>2</codigoPorcentaje><tarifa>12</tarifa><baseImponible>10.26</baseImponible><valor>1.23</valor></impuesto></impuestos></detalle><detalle><codigoPrincipal>23762000</codigoPrincipal><descripcion>TENEDROR DE MESA BUZIOS</descripcion><cantidad>3</cantidad><precioUnitario>4.99</precioUnitario><descuento>0</descuento><precioTotalSinImpuesto>14.97</precioTotalSinImpuesto><impuestos><impuesto><codigo>2</codigo><codigoPorcentaje>2</codigoPorcentaje><tarifa>12</tarifa><baseImponible>14.97</baseImponible><valor>1.8</valor></impuesto></impuestos></detalle></detalles><infoAdicional><campoAdicional nombre='Direccion'>MACARA 10 DE AGOSTO SN Y EMILIANO HERRERA</campoAdicional><campoAdicional nombre='Telefono'>0994647046</campoAdicional><campoAdicional nombre='Email'>sugeya_16_83@hotmail.com</campoAdicional><campoAdicional nombre='Observaciones'>  CREDITO 30  60  75 DIAS</campoAdicional></infoAdicional></factura>