<?xml version='1.0' encoding='UTF-8'?><factura version='1.1.0' id='comprobante'><infoTributaria><ambiente>2</ambiente><tipoEmision>1</tipoEmision><razonSocial>BUELE SARMIENTO MARIA EUGENIA</razonSocial><nombreComercial>IMPORTADORA BYC LA EXCLUSIVIDAD PARA TU HOGAR TRAMONTINA</nombreComercial><ruc>0704384098001</ruc><claveAcceso>0305202301070438409800120010010000001571234567817</claveAcceso><codDoc>01</codDoc><estab>001</estab><ptoEmi>001</ptoEmi><secuencial>000000157</secuencial><dirMatriz>AV. HURTADO DE MEDOZA 10-72 Y BULAN. JUNTO A LA ITALIANA</dirMatriz></infoTributaria><infoFactura><fechaEmision>03/05/2023</fechaEmision><dirEstablecimiento>AV. HURTADO DE MEDOZA 10-72 Y BULAN. JUNTO A LA ITALIANA</dirEstablecimiento><obligadoContabilidad>NO</obligadoContabilidad><tipoIdentificacionComprador>04</tipoIdentificacionComprador><razonSocialComprador>PALLAZHCO YUNGA LUIS JUVENTINO</razonSocialComprador><identificacionComprador>0103662615001</identificacionComprador><totalSinImpuestos>690.59</totalSinImpuestos><totalDescuento>0</totalDescuento><totalConImpuestos><totalImpuesto><codigo>2</codigo><codigoPorcentaje>2</codigoPorcentaje><baseImponible>690.59</baseImponible><valor>82.87</valor></totalImpuesto></totalConImpuestos><propina>0.00</propina><importeTotal>773.46</importeTotal><moneda>DOLAR</moneda><pagos><pago><formaPago>20</formaPago><total>773.46</total></pago></pagos></infoFactura><detalles><detalle><codigoPrincipal>22902007</codigoPrincipal><codigoAuxiliar>FAM.TIP.055</codigoAuxiliar><descripcion>CUCHILLO DE FILETEAR 7</descripcion><cantidad>24</cantidad><precioUnitario>1.75</precioUnitario><descuento>0</descuento><precioTotalSinImpuesto>42</precioTotalSinImpuesto><impuestos><impuesto><codigo>2</codigo><codigoPorcentaje>2</codigoPorcentaje><tarifa>12</tarifa><baseImponible>42</baseImponible><valor>5.04</valor></impuesto></impuestos></detalle><detalle><codigoPrincipal>22902008</codigoPrincipal><codigoAuxiliar>FAM.TIP.056</codigoAuxiliar><descripcion>CUCHILLO DE FILETEAR 8</descripcion><cantidad>24</cantidad><precioUnitario>1.95</precioUnitario><descuento>0</descuento><precioTotalSinImpuesto>46.8</precioTotalSinImpuesto><impuestos><impuesto><codigo>2</codigo><codigoPorcentaje>2</codigoPorcentaje><tarifa>12</tarifa><baseImponible>46.8</baseImponible><valor>5.62</valor></impuesto></impuestos></detalle><detalle><codigoPrincipal>23731004</codigoPrincipal><codigoAuxiliar>FAM.TIP.057</codigoAuxiliar><descripcion>CUCHILLO DE MESA MALIBU Y BUZIOS</descripcion><cantidad>24</cantidad><precioUnitario>0.65</precioUnitario><descuento>0</descuento><precioTotalSinImpuesto>15.6</precioTotalSinImpuesto><impuestos><impuesto><codigo>2</codigo><codigoPorcentaje>2</codigoPorcentaje><tarifa>12</tarifa><baseImponible>15.6</baseImponible><valor>1.87</valor></impuesto></impuestos></detalle><detalle><codigoPrincipal>23737000</codigoPrincipal><codigoAuxiliar>FAM.TIP.234</codigoAuxiliar><descripcion>CUCHARA CAFE MALIBU</descripcion><cantidad>72</cantidad><precioUnitario>0.25</precioUnitario><descuento>0</descuento><precioTotalSinImpuesto>18</precioTotalSinImpuesto><impuestos><impuesto><codigo>2</codigo><codigoPorcentaje>2</codigoPorcentaje><tarifa>12</tarifa><baseImponible>18</baseImponible><valor>2.16</valor></impuesto></impuestos></detalle><detalle><codigoPrincipal>61636103</codigoPrincipal><codigoAuxiliar>FAM.TIP.281</codigoAuxiliar><descripcion>JARRA TERMICA 1 LITRO EXATA</descripcion><cantidad>2</cantidad><precioUnitario>8.75</precioUnitario><descuento>0</descuento><precioTotalSinImpuesto>17.5</precioTotalSinImpuesto><impuestos><impuesto><codigo>2</codigo><codigoPorcentaje>2</codigoPorcentaje><tarifa>12</tarifa><baseImponible>17.5</baseImponible><valor>2.1</valor></impuesto></impuestos></detalle><detalle><codigoPrincipal>61636104</codigoPrincipal><codigoAuxiliar>61636104</codigoAuxiliar><descripcion>JARRA TERMIVA 1 LITRO EXATA MORADA</descripcion><cantidad>2</cantidad><precioUnitario>8.75</precioUnitario><descuento>0</descuento><precioTotalSinImpuesto>17.5</precioTotalSinImpuesto><impuestos><impuesto><codigo>2</codigo><codigoPorcentaje>2</codigoPorcentaje><tarifa>12</tarifa><baseImponible>17.5</baseImponible><valor>2.1</valor></impuesto></impuestos></detalle><detalle><codigoPrincipal>25199007</codigoPrincipal><codigoAuxiliar>FAM.TIP.131</codigoAuxiliar><descripcion>JUEGO UTENSILLOS NYLON</descripcion><cantidad>2</cantidad><precioUnitario>5.03</precioUnitario><descuento>0</descuento><precioTotalSinImpuesto>10.06</precioTotalSinImpuesto><impuestos><impuesto><codigo>2</codigo><codigoPorcentaje>2</codigoPorcentaje><tarifa>12</tarifa><baseImponible>10.06</baseImponible><valor>1.21</valor></impuesto></impuestos></detalle><detalle><codigoPrincipal>61637108</codigoPrincipal><codigoAuxiliar>FAM.TIP.202</codigoAuxiliar><descripcion>T ERMO1 L   BEIG EXATA</descripcion><cantidad>2</cantidad><precioUnitario>9.4</precioUnitario><descuento>0</descuento><precioTotalSinImpuesto>18.8</precioTotalSinImpuesto><impuestos><impuesto><codigo>2</codigo><codigoPorcentaje>2</codigoPorcentaje><tarifa>12</tarifa><baseImponible>18.8</baseImponible><valor>2.26</valor></impuesto></impuestos></detalle><detalle><codigoPrincipal>61641180</codigoPrincipal><codigoAuxiliar>FAM.TIP.211</codigoAuxiliar><descripcion>TERMO C.SIFON 18 LITROS ACERO INOXIDABLE</descripcion><cantidad>4</cantidad><precioUnitario>34.4</precioUnitario><descuento>0</descuento><precioTotalSinImpuesto>137.6</precioTotalSinImpuesto><impuestos><impuesto><codigo>2</codigo><codigoPorcentaje>2</codigoPorcentaje><tarifa>12</tarifa><baseImponible>137.6</baseImponible><valor>16.51</valor></impuesto></impuestos></detalle><detalle><codigoPrincipal>61641120</codigoPrincipal><descripcion>TERMO CON SIFON 1.2 LIT</descripcion><cantidad>3</cantidad><precioUnitario>27.37</precioUnitario><descuento>0</descuento><precioTotalSinImpuesto>82.11</precioTotalSinImpuesto><impuestos><impuesto><codigo>2</codigo><codigoPorcentaje>2</codigoPorcentaje><tarifa>12</tarifa><baseImponible>82.11</baseImponible><valor>9.85</valor></impuesto></impuestos></detalle><detalle><codigoPrincipal>92851009</codigoPrincipal><descripcion>BASURERO COMPACT 7 LTS NEGRO</descripcion><cantidad>1</cantidad><precioUnitario>7.14</precioUnitario><descuento>0</descuento><precioTotalSinImpuesto>7.14</precioTotalSinImpuesto><impuestos><impuesto><codigo>2</codigo><codigoPorcentaje>2</codigoPorcentaje><tarifa>12</tarifa><baseImponible>7.14</baseImponible><valor>0.86</valor></impuesto></impuestos></detalle><detalle><codigoPrincipal>61101020</codigoPrincipal><descripcion>BALANZA DIGITAL TRA. 5KL ACERO INOX.</descripcion><cantidad>4</cantidad><precioUnitario>26.77</precioUnitario><descuento>0</descuento><precioTotalSinImpuesto>107.08</precioTotalSinImpuesto><impuestos><impuesto><codigo>2</codigo><codigoPorcentaje>2</codigoPorcentaje><tarifa>12</tarifa><baseImponible>107.08</baseImponible><valor>12.85</valor></impuesto></impuestos></detalle><detalle><codigoPrincipal>92852009</codigoPrincipal><descripcion>BASURERO COMPACT 10 LTS NEGRO</descripcion><cantidad>1</cantidad><precioUnitario>7.68</precioUnitario><descuento>0</descuento><precioTotalSinImpuesto>7.68</precioTotalSinImpuesto><impuestos><impuesto><codigo>2</codigo><codigoPorcentaje>2</codigoPorcentaje><tarifa>12</tarifa><baseImponible>7.68</baseImponible><valor>0.92</valor></impuesto></impuestos></detalle><detalle><codigoPrincipal>23743000</codigoPrincipal><codigoAuxiliar>FAM.TIP.046</codigoAuxiliar><descripcion>CUCHARA MALIBU</descripcion><cantidad>72</cantidad><precioUnitario>0.41</precioUnitario><descuento>0</descuento><precioTotalSinImpuesto>29.52</precioTotalSinImpuesto><impuestos><impuesto><codigo>2</codigo><codigoPorcentaje>2</codigoPorcentaje><tarifa>12</tarifa><baseImponible>29.52</baseImponible><valor>3.54</valor></impuesto></impuestos></detalle><detalle><codigoPrincipal>23762000</codigoPrincipal><descripcion>TENEDROR DE MESA BUZIOS</descripcion><cantidad>24</cantidad><precioUnitario>0.41</precioUnitario><descuento>0</descuento><precioTotalSinImpuesto>9.84</precioTotalSinImpuesto><impuestos><impuesto><codigo>2</codigo><codigoPorcentaje>2</codigoPorcentaje><tarifa>12</tarifa><baseImponible>9.84</baseImponible><valor>1.18</valor></impuesto></impuestos></detalle><detalle><codigoPrincipal>61530010</codigoPrincipal><descripcion>ESCURRIDOR PARA PLATOS</descripcion><cantidad>2</cantidad><precioUnitario>61.68</precioUnitario><descuento>0</descuento><precioTotalSinImpuesto>123.36</precioTotalSinImpuesto><impuestos><impuesto><codigo>2</codigo><codigoPorcentaje>2</codigoPorcentaje><tarifa>12</tarifa><baseImponible>123.36</baseImponible><valor>14.8</valor></impuesto></impuestos></detalle></detalles><infoAdicional><campoAdicional nombre='Direccion'>AMAZONAS S/N ENTRE LUIS MARQUEZ Y FRACISCO DE ORELLANA</campoAdicional><campoAdicional nombre='Telefono'>0980941844</campoAdicional><campoAdicional nombre='Email'>mundihogar84@hotmail.com</campoAdicional></infoAdicional></factura>